chakra_qtquick-0.5.1.dist-info/licenses/LICENSE
chakra_ui/AppAnimations.qml
chakra_ui/AppStyle.qml
chakra_ui/CActionBar.qml
chakra_ui/CAlert.qml
chakra_ui/CBadge.qml
chakra_ui/CBox.qml
chakra_ui/CButton.qml
chakra_ui/CCard.qml
chakra_ui/CCenter.qml
chakra_ui/CCheckbox.qml
chakra_ui/CContainer.qml
chakra_ui/CDialog.qml
chakra_ui/CDrawer.qml
chakra_ui/CFlex.qml
chakra_ui/CFrameless.py
chakra_ui/CIcon.qml
chakra_ui/CInput.qml
chakra_ui/CMenu.qml
chakra_ui/CMenuGroup.qml
chakra_ui/CMenuItem.qml
chakra_ui/CMenuSeparator.qml
chakra_ui/CPagination.qml
chakra_ui/CProgress.qml
chakra_ui/CScrollArea.qml
chakra_ui/CScrollBar.qml
chakra_ui/CSegmentedControl.qml
chakra_ui/CSelect.qml
chakra_ui/CSpinner.qml
chakra_ui/CSwitch.qml
chakra_ui/CTag.qml
chakra_ui/CTooltip.qml
chakra_ui/CWindow.qml
chakra_ui/Icons.qml
chakra_ui/__init__.py
chakra_ui/qmldir
chakra_ui/fonts/Phosphor.ttf
chakra_qtquick-0.5.1.dist-info/METADATA
chakra_qtquick-0.5.1.dist-info/WHEEL
chakra_qtquick-0.5.1.dist-info/top_level.txt
chakra_qtquick-0.5.1.dist-info/RECORD
