Metadata-Version: 2.4
Name: chakra-qtquick
Version: 0.5.1
Summary: A modern QML component library inspired by Chakra UI
Author-email: ASLant <aslant0607@gmail.com>
License-Expression: MIT
Project-URL: Homepage, https://github.com/Y-ASLant/chakra-ui-qml
Project-URL: Repository, https://github.com/Y-ASLant/chakra-ui-qml
Project-URL: Documentation, https://github.com/Y-ASLant/chakra-ui-qml/tree/main/docs
Project-URL: Issues, https://github.com/Y-ASLant/chakra-ui-qml/issues
Keywords: qml,qt,pyside6,ui,components,chakra-ui
Classifier: Development Status :: 4 - Beta
Classifier: Intended Audience :: Developers
Classifier: Programming Language :: Python :: 3
Classifier: Programming Language :: Python :: 3.8
Classifier: Programming Language :: Python :: 3.9
Classifier: Programming Language :: Python :: 3.10
Classifier: Programming Language :: Python :: 3.11
Classifier: Programming Language :: Python :: 3.12
Classifier: Programming Language :: Python :: 3.13
Classifier: Programming Language :: Python :: 3.14
Classifier: Topic :: Software Development :: User Interfaces
Classifier: Topic :: Software Development :: Libraries :: Python Modules
Requires-Python: >=3.8
License-File: LICENSE
Requires-Dist: pyside6>=6.5.0
Provides-Extra: dev
Requires-Dist: build>=1.2.2.post1; extra == "dev"
Requires-Dist: twine>=6.1.0; extra == "dev"
Dynamic: license-file
